oresat_configs/__init__.py
oresat_configs/__main__.py
oresat_configs/_version.py
oresat_configs/_yaml_to_od.py
oresat_configs/std_objs.py
oresat_configs/configs/__init__.py
oresat_configs/configs/cards_config.py
oresat_configs/configs/edl_config.py
oresat_configs/configs/mission_config.py
oresat_configs/configs/od_config.py
oresat_configs/scripts/__init__.py
oresat_configs/scripts/cards.py.txt
oresat_configs/scripts/edl_commands.py.txt
oresat_configs/scripts/gen_cand.py
oresat_configs/scripts/gen_cand_manager.py
oresat_configs/scripts/gen_canopennode.py
oresat_configs/scripts/gen_dbc.py
oresat_configs/scripts/gen_kaitai.py
oresat_configs/scripts/gen_rst_manager.py
oresat_configs/scripts/gen_xtce.py
oresat_configs-1.0.0.dist-info/licenses/LICENSE
oresat_configs-1.0.0.dist-info/METADATA
oresat_configs-1.0.0.dist-info/WHEEL
oresat_configs-1.0.0.dist-info/entry_points.txt
oresat_configs-1.0.0.dist-info/top_level.txt
oresat_configs-1.0.0.dist-info/RECORD
